contentbased/__init__.py
contentbased/content_based.py
contentbased/content_based_orm.py
contentbased-0.1.0.dist-info/WHEEL
contentbased-0.1.0.dist-info/METADATA
contentbased-0.1.0.dist-info/RECORD
