Metadata-Version: 2.1
Name: contentbased
Version: 0.1.0
Summary: Contentbased Recommender
Author: Crparichaya
Author-email: parichaya.yan@ku.th
Requires-Python: >=3.12,<4.0
Classifier: Programming Language :: Python :: 3
